LICENSE
MANIFEST.in
README.md
setup.py
django_html_emailtemplates.egg-info/PKG-INFO
django_html_emailtemplates.egg-info/SOURCES.txt
django_html_emailtemplates.egg-info/dependency_links.txt
django_html_emailtemplates.egg-info/requires.txt
django_html_emailtemplates.egg-info/top_level.txt
emailtemplates/__init__.py
emailtemplates/admin.py
emailtemplates/apps.py
emailtemplates/fields.py
emailtemplates/models.py
emailtemplates/settings.py
emailtemplates/tests.py
emailtemplates/migrations/0001_initial.py
emailtemplates/migrations/__init__.py
emailtemplates/templates/emailtemplates/base.html
emailtemplates/templates/emailtemplates/base.txt
emailtemplates/templates/emailtemplates/forms/widgets/select.html
emailtemplates/utils/__init__.py
emailtemplates/utils/email.py