Metadata-Version: 2.1
Name: django-html-emailtemplates
Version: 0.0.2
Summary: A simple Django app to create and send editable emails.
Home-page: https://github.com/RG1BB5/django-html-emailtemplates
Author: Rhys Gibbs
Author-email: development@rhysgibbs.co.uk
License: BSD License
Platform: UNKNOWN
Classifier: Environment :: Web Environment
Classifier: Framework :: Django
Classifier: Framework :: Django :: 2.2
Classifier: Intended Audience :: Developers
Classifier: License :: OSI Approved :: BSD License
Classifier: Operating System :: OS Independent
Classifier: Programming Language :: Python
Classifier: Programming Language :: Python :: 3
Classifier: Programming Language :: Python :: 3.4
Classifier: Programming Language :: Python :: 3.5
Classifier: Topic :: Internet :: WWW/HTTP
Classifier: Topic :: Internet :: WWW/HTTP :: Dynamic Content
